hpilo.py
hpilo_fw.py
python_hpilo-4.4.3.data/scripts/hpilo_cli
python_hpilo-4.4.3.dist-info/COPYING
python_hpilo-4.4.3.dist-info/METADATA
python_hpilo-4.4.3.dist-info/WHEEL
python_hpilo-4.4.3.dist-info/top_level.txt
python_hpilo-4.4.3.dist-info/RECORD
